[{"title": "Bitcoin Ecosystem with Andreas M. Antonopoulos", "link": "https://traffic.megaphone.fm/SED6598476129.mp3?_=1"}, {"title": "Moonlight: Software Contracting Platform with Emma Lawler and Philip Thomas", "link": "https://traffic.megaphone.fm/SED3726124078.mp3?_=1"}, {"title": "Service Mesh Deployment with Varun Talwar", "link": "https://traffic.megaphone.fm/SED5465475864.mp3?_=1"}, {"title": "PlayStation Engineering with Tony Godar", "link": "https://traffic.megaphone.fm/SED8441478276.mp3?_=1"}, {"title": "Big Business with Tyler Cowen", "link": "https://traffic.megaphone.fm/SED2613286426.mp3?_=1"}, {"title": "An Elegant Puzzle Virtual Book Club", "link": "https://traffic.megaphone.fm/SED1343477756.mp3?_=1"}, {"title": "a16z Podcasting with Sonal Chokshi", "link": "https://traffic.megaphone.fm/SED3195043991.mp3?_=1"}, {"title": "Data-As-A-Service with Auren Hoffman", "link": "https://traffic.megaphone.fm/SED2634339228.mp3?_=1"}, {"title": "People.ai: Machine Learning for Sales with Andrey Akselrod", "link": "https://traffic.megaphone.fm/SED9113777416.mp3?_=1"}, {"title": "Jaeger: Distributed Tracing at Uber with Yuri Shkuro", "link": "https://traffic.megaphone.fm/SED5894065032.mp3?_=1"}, {"title": "Golden: Intelligent Knowledge Map with Jude Gomila", "link": "https://traffic.megaphone.fm/SED3082471104.mp3?_=1"}, {"title": "Career Karma: Coding Bootcamp Platform with Ruben Harris and Artur Meyster", "link": "https://traffic.megaphone.fm/SED3467082472.mp3?_=1"}, {"title": "Hackathons with Jonathan Gottfried", "link": "https://traffic.megaphone.fm/SED3508922826.mp3?_=1"}, {"title": "TechPrimers: Software Engineering YouTube with Ajay Kumar", "link": "https://traffic.megaphone.fm/SED1853138037.mp3?_=1"}, {"title": "WebAssembly on IoT with Jonathan Beri", "link": "https://traffic.megaphone.fm/SED9391561689.mp3?_=1"}]